pyinilint/__init__.py
pyinilint/__main__.py
pyinilint/pyinilint.py
pyinilint/tests/__init__.py
pyinilint/tests/test_pyinilint.py
pyinilint-0.17.dist-info/AUTHORS
pyinilint-0.17.dist-info/LICENSE.txt
pyinilint-0.17.dist-info/METADATA
pyinilint-0.17.dist-info/WHEEL
pyinilint-0.17.dist-info/entry_points.txt
pyinilint-0.17.dist-info/top_level.txt
pyinilint-0.17.dist-info/RECORD
