Metadata-Version: 2.1
Name: pyinilint
Version: 0.17
Summary: A linter and inspector for INI format files
Home-page: https://gitlab.com/danieljrmay/pyinilint
Author: Daniel J. R. May
Author-email: daniel.may@danieljrmay.com
License: UNKNOWN
Platform: UNKNOWN
Classifier: Programming Language :: Python :: 3
Classifier: License :: OSI Approved :: GNU General Public License v3 (GPLv3)
Classifier: Operating System :: OS Independent
Classifier: Development Status :: 4 - Beta
License-File: LICENSE.txt
License-File: AUTHORS
